Workbook

Sheet Environment
A1: Constraint | B1: Constraint level | C1: Optimisation criterion | D1: type | E1: Latitude (°) | F1: Longitude (°) | G1: Altitude (m) | H1: time resolution (steps/h) | I1: Main grid emissions (gCO2/kWh) | J1: Main grid fossil fuel ratio | K1: Main grid ratio primary over final energy | L1: Connection | M1: Storage model | N1: Production | O1: Meteo | P1: Load | Q1: Terrain type | R1: Tracking | S1: CDSAPI key
A2: Self-sufficiency | B2: 1 | C2: LCOE | D2: pro | E2: -21.0696 | F2: 55.4063 | G2: 1100 | H2: 1 | I2: 730.606 | J2: 0.718 | K2: 2.75 | L2: Off-grid | M2: continuous | N2: automatic | O2: manual | P2: automatic | Q2: parkland, bushes, numerous obstacles | R2: True

Sheet TimeSeries
A1: Datetime | B1: Current_production (W) | C1: Non-controllable load (kW) | D1: Daily movable load (kW) | E1: Yearly movable load (kW)
A2: 01/05/2020 00:00 | B2: 0 | C2: 0.44 | D2: 0 | E2: 0
A3: 01/05/2020 01:00 | B3: 0 | C3: 0.099 | D3: 0 | E3: 0
A4: 01/05/2020 02:00 | B4: 0 | C4: 0.11 | D4: 0 | E4: 0
A5: 01/05/2020 03:00 | B5: 0 | C5: 0.085 | D5: 0 | E5: 0
A6: 01/05/2020 04:00 | B6: 0 | C6: 0.101 | D6: 0 | E6: 0
A7: 01/05/2020 05:00 | B7: 0 | C7: 0.202 | D7: 0 | E7: 0
A8: 01/05/2020 06:00 | B8: 0 | C8: 0.442 | D8: 0 | E8: 0
A9: 01/05/2020 07:00 | B9: 0 | C9: 0.108 | D9: 0 | E9: 0
A10: 01/05/2020 08:00 | B10: 0 | C10: 0.287 | D10: 0 | E10: 0
A11: 01/05/2020 09:00 | B11: 0 | C11: 0.346 | D11: 0 | E11: 0
A12: 01/05/2020 10:00 | B12: 0 | C12: 0.7205 | D12: 0 | E12: 0
A13: 01/05/2020 11:00 | B13: 0 | C13: 0.536 | D13: 0 | E13: 0
... A8761: 30/04/2021 23:00 | B8761: 0 | C8761: 0.539 | D8761: 0 | E8761: 0

Sheet Automatic load specs
A1: Building | B1: Type | C1: Number | D1: Number of users | E1: Min. comfort temperature (°C) | F1: Max. comfort temperature (°C) | G1: Base load | H1: Shared equipment | I1: Electric vehicles | J1: Domestic hot water | K1: IT and office | L1: Light | M1: Thermal comfort
A2: residential1 | B2: residential | C2: 3 | D2: 3 | E2: 23 | F2: 24 | G2: Yes | H2: Yes | I2: Yes | J2: Yes | K2: Yes | L2: Yes | M2: Yes
A3: residential2 | B3: residential | C3: 1 | D3: 5 | E3: 20 | F3: 26 | G3: Yes | H3: Yes | I3: Yes | J3: Yes | K3: Yes | L3: Yes | M3: Yes
A4: faculty | B4: lab | C4: 1 | D4: 450 | E4: 23 | F4: 23 | G4: Yes | H4: Yes | I4: Yes | J4: No | K4: Yes | L4: Yes | M4: Yes
A5: retail | B5: tertiary_retail | C5: 1 | D5: 12 | E5: 22 | F5: 24 | G5: Yes | H5: No | I5: Yes | J5: Yes | K5: Yes | L5: Yes | M5: Yes
A6: food_service | B6: tertiary_food_service | C6: 1 | D6: 70 | E6: 17 | F6: 21 | G6: Yes | H6: Yes | I6: No | J6: Yes | K6: Yes | L6: Yes | M6: Yes

Sheet Load flexibility
A1: Usage | B1: Non movable rate | C1: daily movable rate | D1: yearly movable rate
A2: lighting | B2: 1 | C2: 0 | D2: 0
A3: IT and office equipment | B3: 1 | C3: 0 | D3: 0
A4: shared equipment | B4: 0.5 | C4: 0.5 | D4: 0
A5: electric vehicles | B5: 0 | C5: 1 | D5: 0
A6: domestic hot water | B6: 0 | C6: 1 | D6: 0
A7: heating | B7: 1 | C7: 0 | D7: 0
A8: cooling | B8: 1 | C8: 0 | D8: 0
A9: base | B9: 1 | C9: 0 | D9: 0

Sheet Holidays
A1: holidays dates | B1: vacation start dates | C1: vacation end dates
A2: 45658 | B2: 45658 | C2: 45662
A3: 45768 | B3: 45696 | C3: 45711
A4: 45778 | B4: 45752 | C4: 45768
A5: 45785 | B5: 45843 | C5: 45900
A6: 45806 | B6: 45948 | C6: 45963
A7: 45817 | B7: 46011 | C7: 46022
A8: 45852
A9: 45884
A10: 45962
A11: 45972
A12: 46016

Sheet PV_production_specs
A1: Id | B1: Tilt (°) | C1: Azimuth (°) | D1: Capital unit cost (€) | E1: Operational unit cost (€/yrs) | F1: Lifetime (years) | G1: Capacity | H1: eqCO2 Emissions (gCO2/kWh) | I1: EROI | J1: Module type | K1: Mounting | L1: Module | M1: Inverter | N1: Modules per string | O1: Strings | P1: Surface type | Q1: Surface group
A2: S1 | B2: 21 | C2: 0 | D2: 4000 | E2: 700 | F2: 20 | G2: 3 | H2: 43.9 | I2: 13 | J2: glass-glass | K2: close-mount | L2: Trina_Solar_TSM_385DE14H_II_ | M2: Huawei_Technologies_Co___Ltd___SUN2000_3_8KTL_USL0__240V_ | N2: 6 | O2: 1 | P2: grass | Q2: 1
A3: S2 | B3: 21 | C3: 0 | D3: 6000 | E3: 900 | F3: 20 | G3: 2 | H3: 43.9 | I3: 13 | J3: glass-glass | K3: close-mount | L3: Trina_Solar_TSM_385DE14H_II_ | M3: Huawei_Technologies_Co___Ltd___SUN2000_10KTL_USL0__240V_ | N3: 8 | O3: 1 | P3: grass | Q3: 1
A4: S3 | B4: 21 | C4: 0 | D4: 8000 | E4: 1100 | F4: 20 | G4: 1 | H4: 43.9 | I4: 13 | J4: glass-glass | K4: close-mount | L4: Trina_Solar_TSM_385DE14H_II_ | M4: Huawei_Technologies_Co___Ltd___SUN2000_10KTL_USL0__240V_ | N4: 10 | O4: 1 | P4: grass | Q4: 1
A5: S4 | B5: 21 | C5: 0 | D5: 10000 | E5: 1300 | F5: 20 | G5: 1 | H5: 43.9 | I5: 13 | J5: glass-glass | K5: close-mount | L5: Trina_Solar_TSM_385DE14H_II_ | M5: Huawei_Technologies_Co___Ltd___SUN2000_10KTL_USL0__240V_ | N5: 12 | O5: 1 | P5: grass | Q5: 1
A6: S5 | B6: 21 | C6: 0 | D6: 12000 | E6: 1500 | F6: 20 | G6: 1 | H6: 43.9 | I6: 13 | J6: glass-glass | K6: close-mount | L6: Trina_Solar_TSM_385DE14H_II_ | M6: Huawei_Technologies_Co___Ltd___SUN2000_10KTL_USL0__240V_ | N6: 14 | O6: 1 | P6: grass | Q6: 1
A7: S6 | B7: 21 | C7: 0 | D7: 14000 | E7: 1700 | F7: 20 | G7: 1 | H7: 43.9 | I7: 13 | J7: glass-glass | K7: close-mount | L7: Trina_Solar_TSM_385DE14H_II_ | M7: Huawei_Technologies_Co___Ltd___SUN2000_10KTL_USL0__240V_ | N7: 16 | O7: 1 | P7: grass | Q7: 1
A8: S7 | B8: 21 | C8: 0 | D8: 15000 | E8: 1900 | F8: 20 | G8: 1 | H8: 43.9 | I8: 13 | J8: glass-glass | K8: close-mount | L8: Trina_Solar_TSM_385DE14H_II_ | M8: Huawei_Technologies_Co___Ltd___SUN2000_10KTL_USL0__240V_ | N8: 18 | O8: 1 | P8: grass | Q8: 1
A9: S8 | B9: 0 | C9: 0 | D9: 2000 | E9: 250 | F9: 20 | G9: 18 | H9: 43.9 | I9: 13 | J9: glass-glass | K9: open-rack | L9: Trina_Solar_TSM_385DE14H_II_ | M9: Huawei_Technologies_Co___Ltd___SUN2000_3_8KTL_USL0__240V_ | N9: 2 | O9: 1 | P9: grass | Q9: 2
A10: S9 | B10: 0 | C10: 0 | D10: 3000 | E10: 400 | F10: 20 | G10: 9 | H10: 43.9 | I10: 13 | J10: glass-glass | K10: open-rack | L10: Trina_Solar_TSM_385DE14H_II_ | M10: Huawei_Technologies_Co___Ltd___SUN2000_3_8KTL_USL0__240V_ | N10: 4 | O10: 1 | P10: grass | Q10: 2
A11: S10 | B11: 0 | C11: 0 | D11: 4000 | E11: 600 | F11: 20 | G11: 6 | H11: 43.9 | I11: 13 | J11: glass-glass | K11: open-rack | L11: Trina_Solar_TSM_385DE14H_II_ | M11: Huawei_Technologies_Co___Ltd___SUN2000_3_8KTL_USL0__240V_ | N11: 6 | O11: 1 | P11: grass | Q11: 2
A12: S11 | B12: 0 | C12: 0 | D12: 6000 | E12: 800 | F12: 20 | G12: 4 | H12: 43.9 | I12: 13 | J12: glass-glass | K12: open-rack | L12: Trina_Solar_TSM_385DE14H_II_ | M12: Huawei_Technologies_Co___Ltd___SUN2000_10KTL_USL0__240V_ | N12: 8 | O12: 1 | P12: grass | Q12: 2
A13: S12 | B13: 0 | C13: 0 | D13: 8000 | E13: 1000 | F13: 20 | G13: 3 | H13: 43.9 | I13: 13 | J13: glass-glass | K13: open-rack | L13: Trina_Solar_TSM_385DE14H_II_ | M13: Huawei_Technologies_Co___Ltd___SUN2000_10KTL_USL0__240V_ | N13: 10 | O13: 1 | P13: grass | Q13: 2
... A17: S16 | B17: 0 | C17: 0 | D17: 15000 | E17: 1800 | F17: 20 | G17: 2 | H17: 43.9 | I17: 13 | J17: glass-glass | K17: open-rack | L17: Trina_Solar_TSM_385DE14H_II_ | M17: Huawei_Technologies_Co___Ltd___SUN2000_10KTL_USL0__240V_ | N17: 18 | O17: 1 | P17: grass | Q17: 2

Sheet WT_production_specs
A1: Id | B1: Capital unit cost (€) | C1: Operational unit cost (€/yrs) | D1: Lifetime (years) | E1: Capacity | F1: eqCO2 Emissions (gCO2/kWh) | G1: EROI | H1: Model | I1: Hub height (m) | J1: Surface group
A2: W1 | B2: 5000 | C2: 500 | D2: 20 | E2: 3 | F2: 43.9 | G2: 13 | H2: 1 kW default | I2: 10 | J2: 3
A3: W2 | B3: 20000 | C3: 1500 | D3: 20 | E3: 1 | F3: 43.9 | G3: 13 | H3: 5 kW default | I3: 15 | J3: 4
A4: W3 | B4: 40000 | C4: 2500 | D4: 20 | E4: 1 | F4: 43.9 | G4: 13 | H4: 12 kW default | I4: 20 | J4: 5

Sheet forecasts_generation
A1: Sliding window (days) | B1: AR order | C1: AR coefficients | D1: error bias (%) | E1: magnitude of errors (%) | F1: maximum error coefficient (%) | G1: time horizon (min.)
A2: 15 | B2: 4 | C2: 0.3 | D2: 0 | E2: 10 | F2: 105 | G2: 60
C3: 0.2
C4: 0.1
C5: 0.05

Sheet Unit_productions
A1: Datetime | B1: S1 | C1: S2 | D1: S3 | E1: S4 | F1: S5 | G1: S6 | H1: S7 | I1: S8 | J1: S9 | K1: S10 | L1: S11 | M1: S12 | N1: S13 | O1: S14 | P1: S15 | Q1: S16 | R1: S17 | S1: S18 | T1: S19 | U1: S20 | V1: S21 | W1: S22 | X1: S23
A2: 43952 | B2: 0.00 | C2: 0 | D2: 0 | E2: 0 | F2: 0 | G2: 0 | H2: 0 | I2: 0 | J2: 0 | K2: 0 | L2: 0 | M2: 0 | N2: 0 | O2: 0 | P2: 0 | Q2: 0 | R2: 0 | S2: 0 | T2: 0 | U2: 0 | V2: 0 | W2: 0 | X2: 0
A3: 43952.001 | B3: 0.00 | C3: 0 | D3: 0 | E3: 0 | F3: 0 | G3: 0 | H3: 0 | I3: 0 | J3: 0 | K3: 0 | L3: 0 | M3: 0 | N3: 0 | O3: 0 | P3: 0 | Q3: 0 | R3: 0 | S3: 0 | T3: 0 | U3: 0 | V3: 0 | W3: 0 | X3: 0
A4: 43952.001 | B4: 0.00 | C4: 0 | D4: 0 | E4: 0 | F4: 0 | G4: 0 | H4: 0 | I4: 0 | J4: 0 | K4: 0 | L4: 0 | M4: 0 | N4: 0 | O4: 0 | P4: 0 | Q4: 0 | R4: 0 | S4: 0 | T4: 0 | U4: 0 | V4: 0 | W4: 0 | X4: 0
A5: 43952.002 | B5: 0.00 | C5: 0 | D5: 0 | E5: 0 | F5: 0 | G5: 0 | H5: 0 | I5: 0 | J5: 0 | K5: 0 | L5: 0 | M5: 0 | N5: 0 | O5: 0 | P5: 0 | Q5: 0 | R5: 0 | S5: 0 | T5: 0 | U5: 0 | V5: 0 | W5: 0 | X5: 0
A6: 43952.003 | B6: 0.00 | C6: 0 | D6: 0 | E6: 0 | F6: 0 | G6: 0 | H6: 0 | I6: 0 | J6: 0 | K6: 0 | L6: 0 | M6: 0 | N6: 0 | O6: 0 | P6: 0 | Q6: 0 | R6: 0 | S6: 0 | T6: 0 | U6: 0 | V6: 0 | W6: 0 | X6: 0
A7: 43952.003 | B7: 0.00 | C7: 0.23932406 | D7: 0.3049321 | E7: 0.25171547 | F7: 0.30002064 | G7: 0.24512078 | H7: 0.23574151 | I7: 0.34113806 | J7: 0.23762667 | K7: 0.30290303 | L7: 0.27171158 | M7: 0.23536463 | N7: 0.24202947 | O7: 0.24896781 | P7: 0.23987071 | Q7: 0.26893441 | R7: 0.52704569 | S7: 0.19363492 | T7: 0.21946623 | U7: 0.21946623 | V7: 0.23987071 | W7: 0.20212717 | X7: 0.20665219
A8: 43952.004 | B8: 0.00 | C8: 30.06718 | D8: 58.086683 | E8: 38.452892 | F8: 57.539213 | G8: 38.415877 | H8: 21.297147 | I8: 71.307414 | J8: 38.373749 | K8: 57.360899 | L8: 38.564785 | M8: 37.078644 | N8: 38.398507 | O8: 40.173048 | P8: 39.462291 | Q8: 38.549277 | R8: 39.910855 | S8: 35.817819 | T8: 35.964159 | U8: 35.964159 | V8: 39.462291 | W8: 34.301162 | X8: 36.006769
A9: 43952.005 | B9: 0.00 | C9: 102.6789 | D9: 153.27203 | E9: 118.35164 | F9: 154.02979 | G9: 118.33051 | H9: 80.958552 | I9: 177.71396 | J9: 118.30604 | K9: 151.79383 | L9: 118.41323 | M9: 115.21231 | N9: 118.32048 | O9: 115.37431 | P9: 114.04573 | Q9: 118.40491 | R9: 118.60228 | S9: 115.74507 | T9: 115.8327 | U9: 115.8327 | V9: 114.04573 | W9: 112.7185 | X9: 107.41557
A10: 43952.006 | B10: 0.00 | C10: 185.77823 | D10: 230.13683 | E10: 199.34885 | F10: 232.37802 | G10: 199.36002 | H10: 163.96177 | I10: 253.20577 | J10: 199.37144 | K10: 228.60266 | L10: 199.30814 | M10: 195.97496 | N10: 199.36489 | O10: 189.55884 | P10: 188.32945 | Q10: 199.31443 | R10: 197.194 | S10: 197.0962 | T10: 197.06278 | U10: 197.06278 | V10: 188.32945 | W10: 195.21508 | X10: 182.13592
A11: 43952.006 | B11: 0.00 | C11: 252.75353 | D11: 284.80828 | E11: 262.80104 | F11: 287.47462 | G11: 262.84944 | H11: 234.06324 | I11: 301.89486 | J11: 262.90221 | K11: 283.52969 | L11: 262.64247 | M11: 260.00098 | N11: 262.87149 | O11: 249.4516 | P11: 248.55108 | Q11: 262.6656 | R11: 259.79011 | S11: 258.45544 | T11: 258.28784 | U11: 258.28784 | V11: 248.55108 | W11: 258.80309 | X11: 243.95603
A12: 43952.007 | B12: 0.00 | C12: 299.27241 | D12: 319.24185 | E12: 306.4661 | F12: 321.36225 | G12: 306.54672 | H12: 283.50667 | I12: 328.37327 | J12: 306.63529 | K12: 318.3696 | L12: 306.2055 | M12: 304.60619 | N12: 306.58364 | O12: 292.64376 | P12: 292.11618 | Q12: 306.2432 | R12: 303.95064 | S12: 297.72203 | T12: 297.44757 | U12: 297.44757 | V12: 292.11618 | W12: 300.78507 | X12: 289.33775
A13: 43952.008 | B13: 0.00 | C13: 326.53035 | D13: 335.86083 | E13: 331.8191 | F13: 336.58653 | G13: 331.92092 | H13: 312.94382 | I13: 335.85048 | J13: 332.03305 | K13: 335.49327 | L13: 331.49134 | M13: 331.11184 | N13: 331.96763 | O13: 320.11627 | P13: 319.9518 | Q13: 331.53864 | R13: 329.81543 | S13: 316.71966 | T13: 316.3876 | U13: 316.3876 | V13: 319.9518 | W13: 322.81006 | X13: 318.94307
... A8761: 43958.083 | B8761: 0.00 | C8761: 0 | D8761: 0 | E8761: 0 | F8761: 0 | G8761: 0 | H8761: 0 | I8761: 0 | J8761: 0 | K8761: 0 | L8761: 0 | M8761: 0 | N8761: 0 | O8761: 0 | P8761: 0 | Q8761: 0 | R8761: 0 | S8761: 0 | T8761: 0 | U8761: 0 | V8761: 0 | W8761: 0 | X8761: 0

Sheet Meteo
A1: Datetime | B1: GHI (W/m²) | C1: DNI (W/m²) | D1: DHI (W/m²) | E1: Air temperature (°C) | F1: Wind direction (°) | G1: Wind speed (m/s) | H1: Pressure (hPa) | K1: Variable | L1: Measurement height (m)
A2: 01/05/2020 00:00 | B2: 0 | C2: 0 | D2: 0 | E2: 24.044 | F2: 101.47 | G2: 7.80697 | H2: 984.057 | K2: GHI (W/m²) | L2: 0
A3: 01/05/2020 01:00 | B3: 0 | C3: 0 | D3: 0 | E3: 23.867 | F3: 97.06 | G3: 7.86199 | H3: 983.827 | K3: DNI (W/m²) | L3: 0
A4: 01/05/2020 02:00 | B4: 0 | C4: 0 | D4: 0 | E4: 24.296 | F4: 100.63 | G4: 8.59899 | H4: 983.629 | K4: DHI (W/m²) | L4: 0
A5: 01/05/2020 03:00 | B5: 0 | C5: 0 | D5: 0 | E5: 24.061 | F5: 104.03 | G5: 7.89466 | H5: 983.409 | K5: Air temperature (°C) | L5: 0
A6: 01/05/2020 04:00 | B6: 0 | C6: 0 | D6: 0 | E6: 23.999 | F6: 99.952 | G6: 7.57084 | H6: 983.368 | K6: Wind direction (°) | L6: 0
A7: 01/05/2020 05:00 | B7: 1.2209 | C7: 0 | D7: 1.2209 | E7: 23.751 | F7: 106.52 | G7: 7.51286 | H7: 983.342 | K7: Wind speed (m/s) | L7: 50
A8: 01/05/2020 06:00 | B8: 151.09 | C8: 338.47717 | D8: 84.592004 | E8: 24.882 | F8: 110.835 | G8: 7.73709 | H8: 983.246 | K8: Pressure (hPa) | L8: 0
A9: 01/05/2020 07:00 | B9: 391.4 | C9: 660.70585 | D9: 117.4796 | E9: 26.581 | F9: 97.77 | G9: 8.22162 | H9: 983.451
A10: 01/05/2020 08:00 | B10: 631.59 | C10: 812.07083 | D10: 131.80456 | E10: 27.617 | F10: 109.08 | G10: 7.76631 | H10: 983.949
A11: 01/05/2020 09:00 | B11: 827.6 | C11: 858.35955 | D11: 154.49459 | E11: 28.015 | F11: 119.095 | G11: 7.74199 | H11: 984.466
A12: 01/05/2020 10:00 | B12: 970.7 | C12: 875.85112 | D12: 174.27928 | E12: 28.152 | F12: 116.98 | G12: 7.94384 | H12: 984.86
A13: 01/05/2020 11:00 | B13: 1068 | C13: 901.74373 | D13: 182.2878 | E13: 29.348 | F13: 120.81 | G13: 7.75816 | H13: 985.68
A14: 01/05/2020 12:00 | B14: 1084.1 | C14: 900.44438 | D14: 185.4878 | E14: 29.117 | F14: 119.83 | G14: 8.36008 | H14: 986.092
A15: 01/05/2020 13:00 | B15: 1032 | C15: 892.71657 | D15: 179.04705 | E15: 29.875 | F15: 128.16 | G15: 7.95331 | H15: 987.168
A16: 01/05/2020 14:00 | B16: 916.6 | C16: 877.7138 | D16: 163.90446 | E16: 29.473 | F16: 129.73 | G16: 7.98204 | H16: 988.345
A17: 01/05/2020 15:00 | B17: 733.64 | C17: 821.30872 | D17: 149.66215 | E17: 29.014 | F17: 138.01 | G17: 7.82334 | H17: 989.114
A18: 01/05/2020 16:00 | B18: 509.58 | C18: 708.97227 | D18: 136.7977 | E18: 29.216 | F18: 140.51 | G18: 7.75725 | H18: 989.99
A19: 01/05/2020 17:00 | B19: 281.93 | C19: 566.47667 | D19: 103.64381 | E19: 28.717 | F19: 185.08 | G19: 6.54744 | H19: 990.83
A20: 01/05/2020 18:00 | B20: 69.977 | C20: 217.96276 | D20: 41.548882 | E20: 27.803 | F20: 123.07 | G20: 6.37008 | H20: 991.666
... A8761: 30/04/2021 23:00 | B8761: 0 | C8761: 0 | D8761: 0 | E8761: 22.061 | F8761: 141.78 | G8761: 6.73125 | H8761: 1008.4

Sheet Storage continuous model
A1: Technology | B1: Energy cost (€/kWh) | C1: PCS cost (€/kW) | D1: BOP cost (€/kW) | E1: O&M cost (€/kW-yr.) | F1: Round-trip efficiency | G1: Depth of discharge | H1: Emissions (gCO2eq/kWh) | I1: Lifetime (years) | J1: Cycle life | K1: Installation cost (€) | L1: ESOEI
A2: Li-Ion | B2: =IF(ISBLANK($A2),"",VLOOKUP($A2,Storage_characteristics!$A$2:$L$13,2,FALSE)) -> 750 | C2: =IF(ISBLANK($A2),"",VLOOKUP($A2,Storage_characteristics!$A$2:$J$13,3,FALSE)) -> 442 | D2: =IF(ISBLANK($A2),"",VLOOKUP($A2,Storage_characteristics!$A$2:$J$13,4,FALSE)) -> 30 | E2: =IF(ISBLANK($A2),"",VLOOKUP($A2,Storage_characteristics!$A$2:$J$13,5,FALSE)) -> 62 | F2: =IF(ISBLANK($A2),"",VLOOKUP($A2,Storage_characteristics!$A$2:$J$13,6,FALSE)) -> 0.8 | G2: =IF(ISBLANK($A2),"",VLOOKUP($A2,Storage_characteristics!$A$2:$J$13,7,FALSE)) -> 0.9 | H2: =IF(ISBLANK($A2),"",VLOOKUP($A2,Storage_characteristics!$A$2:$J$13,8,FALSE)) -> 115 | I2: =IF(ISBLANK($A2),"",VLOOKUP($A2,Storage_characteristics!$A$2:$J$13,9,FALSE)) -> 17.5 | J2: =IF(ISBLANK($A2),"",VLOOKUP($A2,Storage_characteristics!$A$2:$J$13,10,FALSE)) -> 6000 | K2: =IF(ISBLANK($A2),"",VLOOKUP($A2,Storage_characteristics!$A$2:$K$13,11,FALSE)) -> 0 | L2: =IF(ISBLANK($A2),"",VLOOKUP($A2,Storage_characteristics!$A$2:$L$13,12,FALSE)) -> 32
B3: =IF(ISBLANK($A3),"",VLOOKUP($A3,Storage_characteristics!$A$2:$L$13,2,FALSE)) | C3: =IF(ISBLANK($A3),"",VLOOKUP($A3,Storage_characteristics!$A$2:$J$13,3,FALSE)) | D3: =IF(ISBLANK($A3),"",VLOOKUP($A3,Storage_characteristics!$A$2:$J$13,4,FALSE)) | E3: =IF(ISBLANK($A3),"",VLOOKUP($A3,Storage_characteristics!$A$2:$J$13,5,FALSE)) | F3: =IF(ISBLANK($A3),"",VLOOKUP($A3,Storage_characteristics!$A$2:$J$13,6,FALSE)) | G3: =IF(ISBLANK($A3),"",VLOOKUP($A3,Storage_characteristics!$A$2:$J$13,7,FALSE)) | H3: =IF(ISBLANK($A3),"",VLOOKUP($A3,Storage_characteristics!$A$2:$J$13,8,FALSE)) | I3: =IF(ISBLANK($A3),"",VLOOKUP($A3,Storage_characteristics!$A$2:$J$13,9,FALSE)) | J3: =IF(ISBLANK($A3),"",VLOOKUP($A3,Storage_characteristics!$A$2:$J$13,10,FALSE)) | K3: =IF(ISBLANK($A3),"",VLOOKUP($A3,Storage_characteristics!$A$2:$K$13,11,FALSE)) | L3: =IF(ISBLANK($A3),"",VLOOKUP($A3,Storage_characteristics!$A$2:$L$13,12,FALSE))
B4: =IF(ISBLANK($A4),"",VLOOKUP($A4,Storage_characteristics!$A$2:$L$13,2,FALSE)) | C4: =IF(ISBLANK($A4),"",VLOOKUP($A4,Storage_characteristics!$A$2:$J$13,3,FALSE)) | D4: =IF(ISBLANK($A4),"",VLOOKUP($A4,Storage_characteristics!$A$2:$J$13,4,FALSE)) | E4: =IF(ISBLANK($A4),"",VLOOKUP($A4,Storage_characteristics!$A$2:$J$13,5,FALSE)) | F4: =IF(ISBLANK($A4),"",VLOOKUP($A4,Storage_characteristics!$A$2:$J$13,6,FALSE)) | G4: =IF(ISBLANK($A4),"",VLOOKUP($A4,Storage_characteristics!$A$2:$J$13,7,FALSE)) | H4: =IF(ISBLANK($A4),"",VLOOKUP($A4,Storage_characteristics!$A$2:$J$13,8,FALSE)) | I4: =IF(ISBLANK($A4),"",VLOOKUP($A4,Storage_characteristics!$A$2:$J$13,9,FALSE)) | J4: =IF(ISBLANK($A4),"",VLOOKUP($A4,Storage_characteristics!$A$2:$J$13,10,FALSE)) | K4: =IF(ISBLANK($A4),"",VLOOKUP($A4,Storage_characteristics!$A$2:$K$13,11,FALSE)) | L4: =IF(ISBLANK($A4),"",VLOOKUP($A4,Storage_characteristics!$A$2:$L$13,12,FALSE))
B5: =IF(ISBLANK($A5),"",VLOOKUP($A5,Storage_characteristics!$A$2:$L$13,2,FALSE)) | C5: =IF(ISBLANK($A5),"",VLOOKUP($A5,Storage_characteristics!$A$2:$J$13,3,FALSE)) | D5: =IF(ISBLANK($A5),"",VLOOKUP($A5,Storage_characteristics!$A$2:$J$13,4,FALSE)) | E5: =IF(ISBLANK($A5),"",VLOOKUP($A5,Storage_characteristics!$A$2:$J$13,5,FALSE)) | F5: =IF(ISBLANK($A5),"",VLOOKUP($A5,Storage_characteristics!$A$2:$J$13,6,FALSE)) | G5: =IF(ISBLANK($A5),"",VLOOKUP($A5,Storage_characteristics!$A$2:$J$13,7,FALSE)) | H5: =IF(ISBLANK($A5),"",VLOOKUP($A5,Storage_characteristics!$A$2:$J$13,8,FALSE)) | I5: =IF(ISBLANK($A5),"",VLOOKUP($A5,Storage_characteristics!$A$2:$J$13,9,FALSE)) | J5: =IF(ISBLANK($A5),"",VLOOKUP($A5,Storage_characteristics!$A$2:$J$13,10,FALSE)) | K5: =IF(ISBLANK($A5),"",VLOOKUP($A5,Storage_characteristics!$A$2:$K$13,11,FALSE)) | L5: =IF(ISBLANK($A5),"",VLOOKUP($A5,Storage_characteristics!$A$2:$L$13,12,FALSE))
B6: =IF(ISBLANK($A6),"",VLOOKUP($A6,Storage_characteristics!$A$2:$L$13,2,FALSE)) | C6: =IF(ISBLANK($A6),"",VLOOKUP($A6,Storage_characteristics!$A$2:$J$13,3,FALSE)) | D6: =IF(ISBLANK($A6),"",VLOOKUP($A6,Storage_characteristics!$A$2:$J$13,4,FALSE)) | E6: =IF(ISBLANK($A6),"",VLOOKUP($A6,Storage_characteristics!$A$2:$J$13,5,FALSE)) | F6: =IF(ISBLANK($A6),"",VLOOKUP($A6,Storage_characteristics!$A$2:$J$13,6,FALSE)) | G6: =IF(ISBLANK($A6),"",VLOOKUP($A6,Storage_characteristics!$A$2:$J$13,7,FALSE)) | H6: =IF(ISBLANK($A6),"",VLOOKUP($A6,Storage_characteristics!$A$2:$J$13,8,FALSE)) | I6: =IF(ISBLANK($A6),"",VLOOKUP($A6,Storage_characteristics!$A$2:$J$13,9,FALSE)) | J6: =IF(ISBLANK($A6),"",VLOOKUP($A6,Storage_characteristics!$A$2:$J$13,10,FALSE)) | K6: =IF(ISBLANK($A6),"",VLOOKUP($A6,Storage_characteristics!$A$2:$K$13,11,FALSE)) | L6: =IF(ISBLANK($A6),"",VLOOKUP($A6,Storage_characteristics!$A$2:$L$13,12,FALSE))
B7: =IF(ISBLANK($A7),"",VLOOKUP($A7,Storage_characteristics!$A$2:$L$13,2,FALSE)) | C7: =IF(ISBLANK($A7),"",VLOOKUP($A7,Storage_characteristics!$A$2:$J$13,3,FALSE)) | D7: =IF(ISBLANK($A7),"",VLOOKUP($A7,Storage_characteristics!$A$2:$J$13,4,FALSE)) | E7: =IF(ISBLANK($A7),"",VLOOKUP($A7,Storage_characteristics!$A$2:$J$13,5,FALSE)) | F7: =IF(ISBLANK($A7),"",VLOOKUP($A7,Storage_characteristics!$A$2:$J$13,6,FALSE)) | G7: =IF(ISBLANK($A7),"",VLOOKUP($A7,Storage_characteristics!$A$2:$J$13,7,FALSE)) | H7: =IF(ISBLANK($A7),"",VLOOKUP($A7,Storage_characteristics!$A$2:$J$13,8,FALSE)) | I7: =IF(ISBLANK($A7),"",VLOOKUP($A7,Storage_characteristics!$A$2:$J$13,9,FALSE)) | J7: =IF(ISBLANK($A7),"",VLOOKUP($A7,Storage_characteristics!$A$2:$J$13,10,FALSE)) | K7: =IF(ISBLANK($A7),"",VLOOKUP($A7,Storage_characteristics!$A$2:$K$13,11,FALSE)) | L7: =IF(ISBLANK($A7),"",VLOOKUP($A7,Storage_characteristics!$A$2:$L$13,12,FALSE))
B8: =IF(ISBLANK($A8),"",VLOOKUP($A8,Storage_characteristics!$A$2:$L$13,2,FALSE)) | C8: =IF(ISBLANK($A8),"",VLOOKUP($A8,Storage_characteristics!$A$2:$J$13,3,FALSE)) | D8: =IF(ISBLANK($A8),"",VLOOKUP($A8,Storage_characteristics!$A$2:$J$13,4,FALSE)) | E8: =IF(ISBLANK($A8),"",VLOOKUP($A8,Storage_characteristics!$A$2:$J$13,5,FALSE)) | F8: =IF(ISBLANK($A8),"",VLOOKUP($A8,Storage_characteristics!$A$2:$J$13,6,FALSE)) | G8: =IF(ISBLANK($A8),"",VLOOKUP($A8,Storage_characteristics!$A$2:$J$13,7,FALSE)) | H8: =IF(ISBLANK($A8),"",VLOOKUP($A8,Storage_characteristics!$A$2:$J$13,8,FALSE)) | I8: =IF(ISBLANK($A8),"",VLOOKUP($A8,Storage_characteristics!$A$2:$J$13,9,FALSE)) | J8: =IF(ISBLANK($A8),"",VLOOKUP($A8,Storage_characteristics!$A$2:$J$13,10,FALSE)) | K8: =IF(ISBLANK($A8),"",VLOOKUP($A8,Storage_characteristics!$A$2:$K$13,11,FALSE)) | L8: =IF(ISBLANK($A8),"",VLOOKUP($A8,Storage_characteristics!$A$2:$L$13,12,FALSE))
B9: =IF(ISBLANK($A9),"",VLOOKUP($A9,Storage_characteristics!$A$2:$L$13,2,FALSE)) | C9: =IF(ISBLANK($A9),"",VLOOKUP($A9,Storage_characteristics!$A$2:$J$13,3,FALSE)) | D9: =IF(ISBLANK($A9),"",VLOOKUP($A9,Storage_characteristics!$A$2:$J$13,4,FALSE)) | E9: =IF(ISBLANK($A9),"",VLOOKUP($A9,Storage_characteristics!$A$2:$J$13,5,FALSE)) | F9: =IF(ISBLANK($A9),"",VLOOKUP($A9,Storage_characteristics!$A$2:$J$13,6,FALSE)) | G9: =IF(ISBLANK($A9),"",VLOOKUP($A9,Storage_characteristics!$A$2:$J$13,7,FALSE)) | H9: =IF(ISBLANK($A9),"",VLOOKUP($A9,Storage_characteristics!$A$2:$J$13,8,FALSE)) | I9: =IF(ISBLANK($A9),"",VLOOKUP($A9,Storage_characteristics!$A$2:$J$13,9,FALSE)) | J9: =IF(ISBLANK($A9),"",VLOOKUP($A9,Storage_characteristics!$A$2:$J$13,10,FALSE)) | K9: =IF(ISBLANK($A9),"",VLOOKUP($A9,Storage_characteristics!$A$2:$K$13,11,FALSE)) | L9: =IF(ISBLANK($A9),"",VLOOKUP($A9,Storage_characteristics!$A$2:$L$13,12,FALSE))

Sheet Storage discrete model
A1: Id | B1: Nominal energy (kWh) | C1: Charge power (kW) | D1: Discharge power (kW) | E1: Capital unit cost (€) | F1: O&M cost (€/yrs) | G1: Round-trip efficiency | H1: Depth of discharge | I1: unit eqCO2 Emissions (gCO2) | J1: Lifetime (years) | K1: Cycle life | L1: ESOEI | M1: Capacity
A2: Li-Ion1 | B2: 20 | C2: 10 | D2: 15 | E2: 5000 | F2: 250 | G2: 0.75 | H2: 0.85 | I2: 1500 | J2: 7 | K2: 5000 | L2: 20 | M2: 100000
A3: Li-Ion2 | B3: 100 | C3: 70 | D3: 75 | E3: 20000 | F3: 1000 | G3: 0.85 | H3: 0.9 | I3: 7000 | J3: 10 | K3: 6000 | L3: 23 | M3: 1000
A4: Li-Ion3 | B4: 1500 | C4: 1200 | D4: 1100 | E4: 200000 | F4: 13000 | G4: 0.93 | H4: 0.95 | I4: 100000 | J4: 15 | K4: 8000 | L4: 26 | M4: 2

Sheet Grid_prices
A1: Contract_Id | B1: Fixed premium (€/kW) | C1: Peak (c€/kWh) | D1: Summer full hours (c€/kWh) | E1: Summer off-peak hours (c€/kWh) | F1: Winter full hours (c€/kWh) | G1: Winter off-peak hours (c€/kWh) | H1: Power overrun (€/kW) | I1: CSPE (c€/kWh) | J1: CTA | K1: TVA load | L1: TVA CTA | M1: Octroi de mer | N1: TGCA | O1: Winter months | P1: Summer months | Q1: Workday peak hours | R1: Workday full hours | S1: Workday off-peak hours | T1: Weekend peak hours | U1: Weekend full hours | V1: Weekend off-peak hours | W1: Selling peak hours | X1: Selling base price (c€/kWh) | Y1: Selling peak price (c€/kWh)
A2: Longues utilisations | B2: 0 | C2: 40 | D2: 40 | E2: 40 | F2: 40 | G2: 40 | H2: 40 | I2: 2.1 | J2: 0 | K2: 0.2 | L2: 0.055 | M2: 0 | N2: 0 | O2: 5 6 7 8 9 | P2: 1 2 3 4 10 11 12 | Q2: 9 10 11 19 20 | R2: 7 8 12 13 14 15 16 17 18 19 21 22 | S2: 23 0 1 2 3 4 5 6 | T2: NA | U2: 7 8 9 10 11 12 13 14 15 16 17 18 19 20 21 22 | V2: 23 0 1 2 3 4 5 6 | W2: 19 20 | X2: 15 | Y2: 35
A3: Moyennes utilisations | B3: 0 | C3: 40 | D3: 40 | E3: 40 | F3: 40 | G3: 40 | H3: 40 | I3: 2.1 | J3: 0 | K3: 0.2 | L3: 0.055 | M3: 0 | N3: 0 | O3: 5 6 7 8 9 | P3: 1 2 3 4 10 11 12 | Q3: 9 10 11 19 20 | R3: 7 8 12 13 14 15 16 17 18 19 21 22 | S3: 23 0 1 2 3 4 5 6 | T3: NA | U3: 7 8 9 10 11 12 13 14 15 16 17 18 19 20 21 22 | V3: 23 0 1 2 3 4 5 6 | W3: 19 20 | X3: 15 | Y3: 35
A4: Courtes utilisations | B4: 0 | C4: 40 | D4: 40 | E4: 40 | F4: 40 | G4: 40 | H4: 40 | I4: 2.1 | J4: 0 | K4: 0.2 | L4: 0.055 | M4: 0 | N4: 0 | O4: 5 6 7 8 9 | P4: 1 2 3 4 10 11 12 | Q4: 9 10 11 19 20 | R4: 7 8 12 13 14 15 16 17 18 19 21 22 | S4: 23 0 1 2 3 4 5 6 | T4: NA | U4: 7 8 9 10 11 12 13 14 15 16 17 18 19 20 21 22 | V4: 23 0 1 2 3 4 5 6 | W4: 19 20 | X4: 15 | Y4: 35
A5: Transition énergétique | B5: 0 | C5: 40 | D5: 40 | E5: 40 | F5: 40 | G5: 40 | H5: 40 | I5: 2.1 | J5: 0 | K5: 0.2 | L5: 0.055 | M5: 0 | N5: 0 | O5: 4 5 6 7 8 9 | P5: 1 2 3 10 11 12 | Q5: 18 19 20 21 | R5: 8 9 10 11 12 13 14 15 16 17 22 23 | S5: 0 1 2 3 4 5 6 7 | T5: NA | U5: 16 17 18 19 20 21 22 23 | V5: 0 1 2 3 4 5 6 7 8 9 10 11 12 13 14 15 | W5: 19 20 | X5: 15 | Y5: 35

Sheet Diesel generator
A1: Parameter | B1: Value | E1: DG fuel consumption
A2: fuel cost (€/L) | B2: 2 | D2: Load (%) | E2: fuel consumption (L/kWh)
A3: Lifetime (h) | B3: 20000 | D3: 10 | E3: 0.55
A4: Unit cost (€/kW) | B4: 800 | D4: 20 | E4: 0.42
A5: maintenance cost (€/kWh) | B5: 0.05 | D5: 30 | E5: 0.37
A6: fuel CO2eq emissions (g/L) | B6: 3100 | D6: 40 | E6: 0.33
A7: EROI | B7: 21 | D7: 50 | E7: 0.31
D8: 60 | E8: 0.3
D9: 70 | E9: 0.3
D10: 80 | E10: 0.29
D11: 90 | E11: 0.29
D12: 100 | E12: 0.28

Sheet Dispatching
A1: Predictive dispatch | C1: Item | D1: User-Defined | F1: Energy use | G1: Repartition coefficients | H1: Storages | I1: Discharge order | J1: SOC (%) | K1: Overlap levels (%) | L1: DG/grid overlap levels (%) | N1: D_DSM minimum levels | P1: Y_DSM minimum levels | R1: Diesel generator
A2: No | C2: Storages management | D2: No | F2: DSM | G2: 0.7 | H2: Li-Ion | I2: 1 | J2: 10 | K2: 60 | L2: 20 | M2: hours | N2: minimum level (%) | O2: months | P2: minimum level (%) | Q2: strategy | R2: LF
C3: DSM | D3: No | F3: storages | G3: 0.3 | H3: CAES (U) | I3: 2 | J3: 20 | K3: 30 | L3: 15 | M3: 0 | N3: 0 | O3: 1 | P3: 0 | Q3: minimum runtime (minutes) | R3: 240
C4: Genset control | D4: No | J4: 30 | K4: 10 | L4: 10 | M4: 1 | N4: 0 | O4: 2 | P4: 0 | Q4: minimum production (kW) | R4: 100
J5: 40 | K5: 0 | L5: 5 | M5: 2 | N5: 0 | O5: 3 | P5: 0
J6: 50 | K6: 0 | L6: 0 | M6: 3 | N6: 0 | O6: 4 | P6: 0
J7: 60 | K7: 0 | L7: 0 | M7: 4 | N7: 0 | O7: 5 | P7: 0
J8: 70 | K8: 0 | L8: 0 | M8: 5 | N8: 0 | O8: 6 | P8: 0
J9: 80 | K9: 0 | L9: 0 | M9: 6 | N9: 0 | O9: 7 | P9: 10
J10: 90 | K10: 0 | L10: 0 | M10: 7 | N10: 0 | O10: 8 | P10: 30
M11: 8 | N11: 0 | O11: 9 | P11: 50
M12: 9 | N12: 0 | O12: 10 | P12: 70
M13: 10 | N13: 0 | O13: 11 | P13: 90
M14: 11 | N14: 0
M15: 12 | N15: 0
M16: 13 | N16: 0
M17: 14 | N17: 0
M18: 15 | N18: 10
M19: 16 | N19: 20
M20: 17 | N20: 30
M21: 18 | N21: 40
M22: 19 | N22: 50
M23: 20 | N23: 60
M24: 21 | N24: 70
M25: 22 | N25: 80

Sheet Hyperparameters
A1: Main parameters | B1: Initialisation values | C1: Evolution values | E1: Operators | F1: Contract | G1: Production | H1: Storage volume | I1: Storage_global | J1: Storage_power | K1: Storage_trades_consistency | L1: Storage_patterns | M1: Inter_storages | N1: Storage_mix | O1: Curve_smoothing | P1: Constraint_forcing | Q1: Interdaily_consistency | R1: DSM_trades_consistency | S1: DSM_noise
A2: Crossover probability | B2: 0.2 | C2: 0.15 | E2: Probability | F2: 0.003 | G2: 0.15 | H2: 0.2 | I2: 0.2 | J2: 0.2 | K2: 0.2 | L2: 0.1 | M2: 0.05 | N2: 0.1 | O2: 0.1 | P2: 0.2 | Q2: 0.15 | R2: 0.1 | S2: 0.1
A3: Elitism probability | B3: 0.6 | C3: 0.6 | E3: Inverse length | F3: 2000 | G3: 15 | H3: 100 | I3: 100 | J3: 100 | K3: 400 | L3: 500 | M3: NA | N3: 700 | O3: 300 | P3: 500 | Q3: 200 | R3: 50 | S3: 50
A4: iterations per island | B4: 3000 | C4: 200 | E4: Min. gaussian average | F4: NA | G4: NA | H4: NA | I4: NA | J4: NA | K4: NA | L4: NA | M4: NA | N4: NA | O4: NA | P4: NA | Q4: NA | R4: 0 | S4: NA
A5: Eras | C5: 4 | E5: Max. gaussian average | F5: NA | G5: NA | H5: 1 | I5: NA | J5: 1 | K5: NA | L5: NA | M5: NA | N5: NA | O5: 0.5 | P5: NA | Q5: NA | R5: 0.7 | S5: NA
A6: population per island | C6: 240 | E6: Min. gaussian deviation | F6: NA | G6: NA | H6: NA | I6: NA | J6: NA | K6: NA | L6: NA | M6: NA | N6: NA | O6: NA | P6: NA | Q6: NA | R6: NA | S6: 0.1
A7: number of nodes | C7: 12 | E7: Max. gaussian deviation | F7: NA | G7: NA | H7: 0.2 | I7: NA | J7: 0.2 | K7: NA | L7: NA | M7: NA | N7: NA | O7: 0.15 | P7: NA | Q7: NA | R7: NA | S7: 0.4
A8: number of cores per node | C8: 25 | E8: Inverse magnitude | H8: 15 | I8: 2 | J8: 15 | K8: 11 | L8: 20 | M8: 1200 | P8: 800 | Q8: 1200 | R8: NA | S8: NA
A9: Constraint cost | B9: 100000 | C9: 100000

Sheet Hyperparameters_pro
A1: Main parameters | B1: Evolution values | D1: Operators | E1: Contract | F1: Production | G1: Strategy | H1: Discharge order | I1: Energy use | J1: Overlap | K1: DSM minimum levels | L1: DG control | M1: storages capacity | N1: storages power | O1: Initial SOC
A2: Crossover probability | B2: 0.15 | D2: Probability | E2: 0.003 | F2: 0.3 | G2: 0.1 | H2: 0.05 | I2: 0.15 | J2: 0.2 | K2: 0.1 | L2: 0.05 | M2: 0.3 | N2: 0.3 | O2: 0.2
A3: Elitism probability | B3: 0.6 | D3: Min. gaussian deviation | E3: NA | F3: 0.3 | G3: NA | H3: NA | I3: 0.3 | J3: 0.3 | K3: 0.2 | L3: 0.2 | M3: 0.2 | N3: 0.2 | O3: NA
A4: iterations | B4: 200
A5: Population | B5: 300
A6: Cost constraint | B6: 100000

Sheet Outputs
A1: File name | B1: export type | C1: export charts
A2: output_ERMESS_pro.xlsx | B2: Excel | C2: True

Sheet Sources
A1: Données réseau Réunion | C1: Les émissions du réseau sont calculées selon le BE Horizon Reunion 2022
A2: https://oer.spl-horizonreunion.com/electricite/consommation-electricite-la-reunion
A3: https://oer.spl-horizonreunion.com/emissions-de-ges/co2-combustion-produits-energetiques#:~:text=Total%20des%20%C3%A9missions%20directes%20de%20CO2%20issues%20de,%C3%A0%20effet%20de%20serre%20dans%20le%20secteur%20%C3%A9nerg%C3%A9tique
A5: Données stockage
A6: Assessment of energy storage technologies: A review
A7: EASE technical sheets
A9: EROI & ESOEI
A10: https://en.wikipedia.org/wiki/Energy_return_on_investment
A12: Courbes de puissance des modèles d'éoliennes par défaut :
A13: turbine-models/turbine_models/data/Distributed at main · NREL/turbine-models
A15: Estimations des longueurs de rugosité
A16: https://en.wikipedia.org/wiki/Roughness_length

Sheet Storage_characteristics
A1: Technology | B1: Energy cost | C1: PCS cost | D1: BOP cost | E1: O&M cost | F1: Round-trip efficiency | G1: Depth of discharge | H1: Emissions | I1: Lifetime | J1: Cycle life | K1: Installation cost | L1: ESOEI
A2: Pumped hydro | B2: 70.5 | C2: 1120 | D2: 16.5 | E2: 6 | F2: 0.8 | G2: 1 | H2: 32 | I2: 80 | J2: NA | K2: 0 | L2: 704 | O2: Self-sufficiency | P2: LCOE | Q2: research | R2: True | S2: LF | T2: On-grid | U2: glass-glass | V2: open-rack | W2: grass | X2: manual | Y2: off-shore | Z2: Excel | AA2: discrete | AB2: tertiary_retail | AC2: Yes
A3: CAES (A) | B3: 117 | C3: 914 | D3: 16.5 | E3: 3 | F3: 0.7 | G3: 1 | H3: 160 | I3: 30 | J3: NA | K3: 0 | L3: 792 | O3: Self-consumption | P3: Annual net benefits | Q3: pro | R3: False | S3: CC | T3: Off-grid | U3: glass-polymer | V3: close-mount | W3: concrete | X3: automatic | Y3: no vegetation, no obstacles | AA3: continuous | AB3: residential | AC3: No
A4: CAES (U) | B4: 66 | C4: 1053 | D4: 16.5 | E4: 3.5 | F4: 0.7 | G4: 1 | H4: 160 | I4: 30 | J4: NA | K4: 0 | L4: 792 | O4: REN fraction | P4: NPV | W4: asphalt | Y4: flat terrain, grass, isloated obstacles | AB4: dormitory
A5: Flywheel | B5: 3500 | C5: 354 | D5: 150 | E5: 5.5 | F5: 0.9 | G5: 1 | H5: 1500 | I5: 15 | J5: NA | K5: 0 | P5: Self-sufficiency | W5: snow | Y5: low crops, occasional obstacles | AB5: teaching
A6: Pb-A (Lead-Acid) | B6: 220 | C6: 442 | D6: 72 | E6: 14.5 | F6: 0.8 | G6: 0.9 | H6: 112 | I6: 10 | J6: 1500 | K6: 0 | L6: 5 | P6: Self-consumption | W6: water | Y6: high crops, scattered obstacles | AB6: lab
A7: Li-Ion | B7: 750 | C7: 442 | D7: 30 | E7: 62 | F7: 0.8 | G7: 0.9 | H7: 115 | I7: 17.5 | J7: 6000 | K7: 0 | L7: 32 | P7: Autonomy | W7: sand | Y7: parkland, bushes, numerous obstacles | AB7: office
A8: Na-S (Sodium-Sulfur) | B8: 860 | C8: 442 | D8: 99 | E8: 26 | F8: 0.85 | G8: 1 | H8: 115 | I8: 17.5 | J8: 6000 | K8: 0 | L8: 20 | P8: eqCO2 emissions | W8: urban | Y8: regular large obstacles (suburbs, forest) | AB8: tertiary_hospitality
A9: Ni-Cd (Nickel Cadmium) | B9: 909.5 | C9: 318 | D9: 102 | E9: 15 | F9: 0.8 | G9: 0.9 | H9: 115 | I9: 15 | J9: 3000 | K9: 0 | P9: fossil fuel consumption | Y9: city centre | AB9: tertiary_food_service
A10: Vanadium Redox | B10: 611 | C10: 442 | D10: 92 | E10: 27.5 | F10: 0.85 | G10: 1 | H10: 115 | I10: 15 | J10: 15000 | K10: 0 | L10: 10 | P10: EROI | AB10: tertiary_healthcare
A11: ZnBr (Zinc-Bromine) | B11: 487.5 | C11: 442 | D11: 92 | E11: 5 | F11: 0.85 | G11: 1 | H11: 115 | I11: 15 | J11: 3000 | K11: 0 | L11: 9 | P11: Energy losses | AB11: tertiary_public_services
A12: Hydrogen | B12: 8.5 | C12: 860 | D12: 20 | E12: 32.5 | F12: 0.5 | G12: 1 | H12: 350 | I12: 20 | J12: NA | K12: 0 | P12: Maximum power from grid
A13: Supercapacitor | B13: 2200 | C13: 354 | D13: 50 | E13: 3.5 | F13: 0.6 | G13: 1 | H13: 1000 | I13: 40 | J13: NA | K13: 0

Sheet Storage characteristics_IRENA
A1: Technology | B1: Energy cost | C1: Power cost | D1: Round-trip efficiency | E1: Depth of discharge
A2: Li-Ion (LFP) | B2: 314.2 | C2: 65.6 | D2: 0.931 | E2: 0.9
A3: Li-Ion (NCA) | B3: 199.1 | C3: 65.6 | D3: 0.961 | E3: 0.9
A4: Li-Ion (NMC) | B4: 232.4 | C4: 65.6 | D4: 0.961 | E4: 0.9
A5: Li-Ion (Titanate) | B5: 633.1 | C5: 65.6 | D5: 0.971 | E5: 0.95
A6: NaNiCl | B6: 222.9 | C6: 65.6 | D6: 0.86 | E6: 1
A7: NaS | B7: 217 | C7: 65.6 | D7: 0.956 | E7: 1
A8: Vanadium Flow | B8: 174.2 | C8: 65.6 | D8: 0.751 | E8: 1
A9: ZnBr Flow | B9: 452.3 | C9: 65.6 | D9: 0.751 | E9: 1
